logging_slack_email/__init__.py
logging_slack_email/logger.py
pyalert_slackemail-0.1.0.dist-info/METADATA
pyalert_slackemail-0.1.0.dist-info/WHEEL
pyalert_slackemail-0.1.0.dist-info/top_level.txt
pyalert_slackemail-0.1.0.dist-info/RECORD
