Metadata-Version: 2.2
Name: pyalert-slackemail
Version: 0.1.0
Summary: A Package for creating default logs and posting logs to slack and email
Author: Vaibhav Kharatmal
Author-email: vaibhav.kharatmal@shreemaruti.com
Classifier: Programming Language :: Python :: 3
Classifier: License :: OSI Approved :: MIT License
Classifier: Operating System :: OS Independent
Requires-Python: >=3.6
Dynamic: author
Dynamic: author-email
Dynamic: classifier
Dynamic: requires-python
Dynamic: summary
